Metadata-Version: 2.1
Name: ndf
Version: 0.1.4
Summary: NumPy based deep learning framework
Home-page: https://github.com/primozgodec/ndf
Author: Primoz Godec
Author-email: primoz492@gmail.com
License: UNKNOWN
Platform: UNKNOWN
Classifier: Programming Language :: Python :: 3
Classifier: Operating System :: OS Independent
